src/blinky.sv

// Hardware Logic: A simple 4-bit counter that toggles an LED
module blinky (
    input  logic clk,
    input  logic rst,
    output logic led
);

    logic [3:0] count;

    always_ff @(posedge clk or posedge rst) begin
        if (rst) begin
            count <= 4'b0;
            led   <= 1'b0;
        end else begin
            count <= count + 1;
            // Toggle LED when the counter reaches 15 (hex 'f')
            if (count == 4'hf) begin
                led <= ~led;
            end
        end
    end

endmodule

blinky_sim/waveform.vcd
$version Generated by VerilatedVcd $end
$timescale 1ps $end
 $scope module TOP $end
  $var wire 1 # clk $end
  $var wire 1 $ rst $end
  $var wire 1 % led $end
  $scope module blinky $end
   $var wire 1 # clk $end
   $var wire 1 $ rst $end
   $var wire 1 % led $end
   $var wire 4 & count [3:0] $end
  $upscope $end
 $upscope $end
$enddefinitions $end


#0
1#
1$
0%
b0000 &
#1
0#
#2
1#
#3
0#
#4
1#
#5
0#
#6
1#
#7
0#
#8
1#
#9
0#
#10
1#
#11
0#
0$
#12
1#
b0001 &
#13
0#
#14
1#
b0010 &
#15
0#
#16
1#
b0011 &
#17
0#
#18
1#
b0100 &
#19
0#
#20
1#
b0101 &
#21
0#
#22
1#
b0110 &
#23
0#
#24
1#
b0111 &
#25
0#
#26
1#
b1000 &
#27
0#
#28
1#
b1001 &
#29
0#
#30
1#
b1010 &
#31
0#
#32
1#
b1011 &
#33
0#
#34
1#
b1100 &
#35
0#
#36
1#
b1101 &
#37
0#
#38
1#
b1110 &
#39
0#
#40
1#
b1111 &
#41
0#
#42
1#
1%
b0000 &
#43
0#
#44
1#
b0001 &
#45
0#
#46
1#
b0010 &
#47
0#
#48
1#
b0011 &
#49
0#
#50
1#
b0100 &
#51
0#
#52
1#
b0101 &
#53
0#
#54
1#
b0110 &
#55
0#
#56
1#
b0111 &
#57
0#
#58
1#
b1000 &
#59
0#
#60
1#
b1001 &
#61
0#
#62
1#
b1010 &
#63
0#
#64
1#
b1011 &
#65
0#
#66
1#
b1100 &
#67
0#
#68
1#
b1101 &
#69
0#
#70
1#
b1110 &
#71
0#
#72
1#
b1111 &
#73
0#
#74
1#
0%
b0000 &
#75
0#
#76
1#
b0001 &
#77
0#
#78
1#
b0010 &
#79
0#
#80
1#
b0011 &
#81
0#
#82
1#
b0100 &
#83
0#
#84
1#
b0101 &
#85
0#
#86
1#
b0110 &
#87
0#
#88
1#
b0111 &
#89
0#
#90
1#
b1000 &
#91
0#
#92
1#
b1001 &
#93
0#
#94
1#
b1010 &
#95
0#
#96
1#
b1011 &
#97
0#
#98
1#
b1100 &
