ideas/mac_unit_without_saturation.sv
`timescale 1ns/1ps

module mac_unit #(
    parameter WIDTH = 16  // Q8.8 format
)(
    input  logic              clk,
    input  logic              rst_n,
    input  logic              en,       // Enable processing
    input  logic              clr,      // Clear the accumulator
    input  logic signed [WIDTH-1:0] a_in,
    input  logic signed [WIDTH-1:0] b_in,
    output logic signed [(WIDTH*2)-1:0] out  // Double width to prevent overflow
);

    // Pipeline Registers
    logic signed [(WIDTH*2)-1:0] mult_reg;
    logic signed [(WIDTH*2)-1:0] acc_reg;

    // --- STAGE 1: Multiplication ---
    always_ff @(posedge clk or negedge rst_n) begin
        if (!rst_n) begin
            mult_reg <= '0;
        end else if (en) begin
            mult_reg <= a_in * b_in;
        end
    end

    // --- STAGE 2: Accumulation ---
    always_ff @(posedge clk or negedge rst_n) begin
        if (!rst_n) begin
            acc_reg <= '0;
        end else if (clr) begin
            acc_reg <= '0;
        end else if (en) begin
            // We add the previous multiplication result to the accumulator
            acc_reg <= acc_reg + mult_reg;
        end
    end

    // Continuous assignment to output
    assign out = acc_reg;

endmodule

2stage_Mac_sim/waveform.vcd
$version Generated by VerilatedVcd $end
$timescale 1ps $end
 $scope module TOP $end
  $var wire 1 # clk $end
  $var wire 1 $ rst_n $end
  $var wire 1 % en $end
  $var wire 1 & clr $end
  $var wire 16 ' a_in [15:0] $end
  $var wire 16 ( b_in [15:0] $end
  $var wire 32 ) out [31:0] $end
  $scope module mac_unit $end
   $var wire 32 , WIDTH [31:0] $end
   $var wire 1 # clk $end
   $var wire 1 $ rst_n $end
   $var wire 1 % en $end
   $var wire 1 & clr $end
   $var wire 16 ' a_in [15:0] $end
   $var wire 16 ( b_in [15:0] $end
   $var wire 32 ) out [31:0] $end
   $var wire 32 * mult_reg [31:0] $end
   $var wire 32 + acc_reg [31:0] $end
  $upscope $end
 $upscope $end
$enddefinitions $end


#0
0#
0$
0%
0&
b0000000000000000 '
b0000000000000000 (
b00000000000000000000000000000000 )
b00000000000000000000000000000000 *
b00000000000000000000000000000000 +
b00000000000000000000000000010000 ,
#1
1#
#2
0#
1$
#3
1#
#4
0#
1%
b0000000000000010 '
b0000000000000011 (
#5
1#
b00000000000000000000000000000110 *
#6
0#
b0000000000000100 '
b0000000000000101 (
#7
1#
b00000000000000000000000000000110 )
b00000000000000000000000000010100 *
b00000000000000000000000000000110 +
#8
0#
b0000000000000000 '
b0000000000000000 (
#9
1#
b00000000000000000000000000011010 )
b00000000000000000000000000000000 *
b00000000000000000000000000011010 +
